Metadata-Version: 2.2
Name: manticore-orderbook
Version: 1.0.1
Summary: A high-performance order book implementation for cryptocurrency exchanges
Home-page: https://github.com/manticoretechnologies/manticore-orderbook
Author: Manticore Technologies
Author-email: dev@manticore.technology
License: MIT
Project-URL: Homepage, https://manticore.technology
Project-URL: GitHub, https://github.com/manticoretechnologies/manticore-orderbook
Project-URL: Bug Tracker, https://github.com/manticoretechnologies/manticore-orderbook/issues
Classifier: Programming Language :: Python :: 3
Classifier: License :: OSI Approved :: MIT License
Classifier: Operating System :: OS Independent
Classifier: Intended Audience :: Financial and Insurance Industry
Classifier: Topic :: Office/Business :: Financial :: Investment
Requires-Python: >=3.8
License-File: LICENSE
Requires-Dist: tabulate>=0.8.9
Provides-Extra: benchmark
Requires-Dist: tabulate>=0.8.9; extra == "benchmark"
Provides-Extra: dev
Requires-Dist: pytest>=7.0.0; extra == "dev"
Requires-Dist: pytest-cov>=4.0.0; extra == "dev"
Requires-Dist: tabulate>=0.8.9; extra == "dev"
Dynamic: author-email
Dynamic: home-page
Dynamic: requires-python
